nostalgiaforever/__init__.py
nostalgiaforever/_version.py
nostalgiaforever/importing.ipynb
nostalgiaforever/informal_script.py
nostalgiaforever/ipyconfig.py
nostalgiaforever/plugin.ipynb
nostalgiaforever/plugin.py
nostalgiaforever/reuse.ipynb
nostalgiaforever/testing.ipynb
nostalgiaforever/util.ipynb
nostalgiaforever-0.0.3.dist-info/METADATA
nostalgiaforever-0.0.3.dist-info/RECORD
nostalgiaforever-0.0.3.dist-info/WHEEL
nostalgiaforever-0.0.3.dist-info/entry_points.txt
nostalgiaforever-0.0.3.dist-info/top_level.txt
