Metadata-Version: 2.1
Name: nostalgiaforever
Version: 0.0.3
Summary: Import .ipynb files as modules in the system path.
Home-page: https://github.com/deathbeds/nostalgiaforever
Author: deathbeds
Author-email: tony.fast@gmail.com
License: BSD-3-Clause
Platform: UNKNOWN
Classifier: Development Status :: 4 - Beta
Classifier: Framework :: IPython
Classifier: Framework :: Jupyter
Classifier: Intended Audience :: Developers
Classifier: Natural Language :: English
Classifier: Programming Language :: Python
Classifier: Programming Language :: Python :: 3.6
Requires-Dist: ipython
Requires-Dist: watchdog
Requires-Dist: pytest
Requires-Dist: importnb
Requires-Dist: pidgin
Requires-Dist: numba
